financial_dataset_loader/__init__.py
financial_dataset_loader/data_source.py
financial_dataset_loader/dataset_loader_config.py
financial_dataset_loader/dataset_loader_local.py
financial_dataset_loader/dataset_loader_s3.py
financial_dataset_loader/dataset_loader_universal.py
financial_dataset_loader/file_name_formatter.py
financial_dataset_loader/path_director.py
financial_dataset_loader-0.2.8.dist-info/METADATA
financial_dataset_loader-0.2.8.dist-info/WHEEL
financial_dataset_loader-0.2.8.dist-info/top_level.txt
financial_dataset_loader-0.2.8.dist-info/RECORD
