Metadata-Version: 2.4
Name: financial_dataset_loader
Version: 0.2.8
Summary: A Python module for loading financial datasets from various sources
Home-page: https://github.com/nailen1/financial_dataset_loader.git
Author: June Young Park
Author-email: juneyoungpaak@gmail.com
Keywords: financial data loader dataset aws s3
Classifier: Development Status :: 3 - Alpha
Classifier: Intended Audience :: Developers
Classifier: Intended Audience :: Financial and Insurance Industry
Classifier: Topic :: Software Development :: Libraries :: Python Modules
Classifier: Topic :: Office/Business :: Financial
Classifier: Programming Language :: Python :: 3
Classifier: Programming Language :: Python :: 3.11
Classifier: License :: OSI Approved :: MIT License
Classifier: Operating System :: OS Independent
Requires-Python: >=3.11
Requires-Dist: shining_pebbles
Requires-Dist: aws-s3-controller>=0.7.4
Requires-Dist: string_date_controller>=0.1.1
Dynamic: author
Dynamic: author-email
Dynamic: classifier
Dynamic: description
Dynamic: description-content-type
Dynamic: home-page
Dynamic: keywords
Dynamic: requires-dist
Dynamic: requires-python
Dynamic: summary
